snowflake/snowpark_checkpoints/__init__.py
snowflake/snowpark_checkpoints/__version__.py
snowflake/snowpark_checkpoints/checkpoint.py
snowflake/snowpark_checkpoints/errors.py
snowflake/snowpark_checkpoints/job_context.py
snowflake/snowpark_checkpoints/singleton.py
snowflake/snowpark_checkpoints/snowpark_sampler.py
snowflake/snowpark_checkpoints/spark_migration.py
snowflake/snowpark_checkpoints/validation_result_metadata.py
snowflake/snowpark_checkpoints/validation_results.py
snowflake/snowpark_checkpoints/io_utils/__init__.py
snowflake/snowpark_checkpoints/io_utils/io_default_strategy.py
snowflake/snowpark_checkpoints/io_utils/io_env_strategy.py
snowflake/snowpark_checkpoints/io_utils/io_file_manager.py
snowflake/snowpark_checkpoints/utils/__init__.py
snowflake/snowpark_checkpoints/utils/constants.py
snowflake/snowpark_checkpoints/utils/extra_config.py
snowflake/snowpark_checkpoints/utils/logging_utils.py
snowflake/snowpark_checkpoints/utils/pandera_check_manager.py
snowflake/snowpark_checkpoints/utils/supported_types.py
snowflake/snowpark_checkpoints/utils/telemetry.py
snowflake/snowpark_checkpoints/utils/utils_checks.py
snowpark_checkpoints_validators-0.4.0.dist-info/METADATA
snowpark_checkpoints_validators-0.4.0.dist-info/WHEEL
snowpark_checkpoints_validators-0.4.0.dist-info/licenses/LICENSE
snowpark_checkpoints_validators-0.4.0.dist-info/RECORD
